kfinance_assistant/__init__.py
kfinance_assistant/assistant.py
kfinance_assistant-1.0.0.dist-info/LICENSE
kfinance_assistant-1.0.0.dist-info/METADATA
kfinance_assistant-1.0.0.dist-info/WHEEL
kfinance_assistant-1.0.0.dist-info/top_level.txt
kfinance_assistant-1.0.0.dist-info/RECORD
