Metadata-Version: 2.1
Name: kfinance_assistant
Version: 1.0.0
Summary: Система для управления финансами и анализа расходов.
Home-page: https://github.com/artemkuerton/kfinance_assistant
Author: Kuerton
Author-email: contact@maliont.games
Classifier: Programming Language :: Python :: 3
Classifier: License :: OSI Approved :: MIT License
Classifier: Operating System :: OS Independent
Requires-Python: >=3.6
License-File: LICENSE
